{
    "networks": {
        "s0": null,
        "s1": {
            "s0": {
                "bw": 1000,
                "delay": "147ms",
                "loss": 0.0028,
                "max_queue_size": 100000
            }
        },
        "s2": null,
        "s3": null,
        "s4": {
            "s1": {
                "bw": 1000,
                "delay": "85ms",
                "loss": 0.0143,
                "max_queue_size": 100000
            }
        },
        "s5": null,
        "s6": null,
        "s7": null,
        "s8": null,
        "s9": {
            "s2": {
                "bw": 1000,
                "delay": "90ms",
                "loss": 0.0012,
                "max_queue_size": 100000
            },
            "s7": {
                "bw": 1000,
                "delay": "38ms",
                "loss": 0.0006,
                "max_queue_size": 100000
            }
        },
        "s10": null,
        "s11": null,
        "s12": {
            "s7": {
                "bw": 1000,
                "delay": "117ms",
                "loss": 0.0085,
                "max_queue_size": 100000
            }
        },
        "s13": {
            "s5": {
                "bw": 1000,
                "delay": "139ms",
                "loss": 0.0029,
                "max_queue_size": 100000
            },
            "s6": {
                "bw": 1000,
                "delay": "24ms",
                "loss": 0.0007,
                "max_queue_size": 100000
            },
            "s9": {
                "bw": 1000,
                "delay": "114ms",
                "loss": 0.0021,
                "max_queue_size": 100000
            }
        },
        "s14": {
            "s8": {
                "bw": 1000,
                "delay": "117ms",
                "loss": 0.0048,
                "max_queue_size": 100000
            },
            "s10": {
                "bw": 1000,
                "delay": "97ms",
                "loss": 0.0032,
                "max_queue_size": 100000
            }
        },
        "s15": {
            "s0": {
                "bw": 1000,
                "delay": "60ms",
                "loss": 0.0042,
                "max_queue_size": 100000
            },
            "s9": {
                "bw": 1000,
                "delay": "34ms",
                "loss": 0.0006,
                "max_queue_size": 100000
            },
            "s11": {
                "bw": 1000,
                "delay": "49ms",
                "loss": 0.0124,
                "max_queue_size": 100000
            },
            "s14": {
                "bw": 1000,
                "delay": "146ms",
                "loss": 0.0093,
                "max_queue_size": 100000
            },
            "s3": {
                "bw": 1000,
                "delay": "29ms",
                "loss": 0.0228,
                "max_queue_size": 100000
            }
        }
    },
    "peers": {
        "h0": {
            "s12": {
                "bw": 10,
                "delay": "10ms",
                "loss": 1,
                "max_queue_size": 1000
            }
        },
        "h1": {
            "s5": {
                "bw": 10,
                "delay": "10ms",
                "loss": 1,
                "max_queue_size": 1000
            }
        },
        "h2": {
            "s3": {
                "bw": 10,
                "delay": "10ms",
                "loss": 1,
                "max_queue_size": 1000
            }
        },
        "h3": {
            "s7": {
                "bw": 10,
                "delay": "10ms",
                "loss": 1,
                "max_queue_size": 1000
            }
        },
        "h4": {
            "s15": {
                "bw": 10,
                "delay": "10ms",
                "loss": 1,
                "max_queue_size": 1000
            }
        },
        "h5": {
            "s5": {
                "bw": 10,
                "delay": "10ms",
                "loss": 1,
                "max_queue_size": 1000
            }
        },
        "h6": {
            "s12": {
                "bw": 10,
                "delay": "10ms",
                "loss": 1,
                "max_queue_size": 1000
            }
        },
        "h7": {
            "s5": {
                "bw": 10,
                "delay": "10ms",
                "loss": 1,
                "max_queue_size": 1000
            }
        },
        "h8": {
            "s9": {
                "bw": 10,
                "delay": "10ms",
                "loss": 1,
                "max_queue_size": 1000
            }
        },
        "h9": {
            "s7": {
                "bw": 10,
                "delay": "10ms",
                "loss": 1,
                "max_queue_size": 1000
            }
        },
        "h10": {
            "s1": {
                "bw": 10,
                "delay": "10ms",
                "loss": 1,
                "max_queue_size": 1000
            }
        },
        "h11": {
            "s10": {
                "bw": 10,
                "delay": "10ms",
                "loss": 1,
                "max_queue_size": 1000
            }
        },
        "h12": {
            "s1": {
                "bw": 10,
                "delay": "10ms",
                "loss": 1,
                "max_queue_size": 1000
            }
        },
        "h13": {
            "s14": {
                "bw": 10,
                "delay": "10ms",
                "loss": 1,
                "max_queue_size": 1000
            }
        },
        "h14": {
            "s5": {
                "bw": 10,
                "delay": "10ms",
                "loss": 1,
                "max_queue_size": 1000
            }
        },
        "h15": {
            "s2": {
                "bw": 10,
                "delay": "10ms",
                "loss": 1,
                "max_queue_size": 1000
            }
        },
        "h16": {
            "s14": {
                "bw": 10,
                "delay": "10ms",
                "loss": 1,
                "max_queue_size": 1000
            }
        },
        "h17": {
            "s5": {
                "bw": 10,
                "delay": "10ms",
                "loss": 1,
                "max_queue_size": 1000
            }
        },
        "h18": {
            "s15": {
                "bw": 10,
                "delay": "10ms",
                "loss": 1,
                "max_queue_size": 1000
            }
        },
        "h19": {
            "s1": {
                "bw": 10,
                "delay": "10ms",
                "loss": 1,
                "max_queue_size": 1000
            }
        },
        "h20": {
            "s3": {
                "bw": 10,
                "delay": "10ms",
                "loss": 1,
                "max_queue_size": 1000
            }
        },
        "h21": {
            "s7": {
                "bw": 10,
                "delay": "10ms",
                "loss": 1,
                "max_queue_size": 1000
            }
        },
        "h22": {
            "s14": {
                "bw": 10,
                "delay": "10ms",
                "loss": 1,
                "max_queue_size": 1000
            }
        },
        "h23": {
            "s11": {
                "bw": 10,
                "delay": "10ms",
                "loss": 1,
                "max_queue_size": 1000
            }
        },
        "h24": {
            "s2": {
                "bw": 10,
                "delay": "10ms",
                "loss": 1,
                "max_queue_size": 1000
            }
        },
        "h25": {
            "s3": {
                "bw": 10,
                "delay": "10ms",
                "loss": 1,
                "max_queue_size": 1000
            }
        },
        "h26": {
            "s6": {
                "bw": 10,
                "delay": "10ms",
                "loss": 1,
                "max_queue_size": 1000
            }
        },
        "h27": {
            "s7": {
                "bw": 10,
                "delay": "10ms",
                "loss": 1,
                "max_queue_size": 1000
            }
        },
        "h28": {
            "s6": {
                "bw": 10,
                "delay": "10ms",
                "loss": 1,
                "max_queue_size": 1000
            }
        },
        "h29": {
            "s12": {
                "bw": 10,
                "delay": "10ms",
                "loss": 1,
                "max_queue_size": 1000
            }
        },
        "h30": {
            "s15": {
                "bw": 10,
                "delay": "10ms",
                "loss": 1,
                "max_queue_size": 1000
            }
        },
        "h31": {
            "s1": {
                "bw": 10,
                "delay": "10ms",
                "loss": 1,
                "max_queue_size": 1000
            }
        },
        "h32": {
            "s7": {
                "bw": 10,
                "delay": "10ms",
                "loss": 1,
                "max_queue_size": 1000
            }
        },
        "h33": {
            "s2": {
                "bw": 10,
                "delay": "10ms",
                "loss": 1,
                "max_queue_size": 1000
            }
        },
        "h34": {
            "s10": {
                "bw": 10,
                "delay": "10ms",
                "loss": 1,
                "max_queue_size": 1000
            }
        },
        "h35": {
            "s7": {
                "bw": 10,
                "delay": "10ms",
                "loss": 1,
                "max_queue_size": 1000
            }
        },
        "h36": {
            "s0": {
                "bw": 10,
                "delay": "10ms",
                "loss": 1,
                "max_queue_size": 1000
            }
        },
        "h37": {
            "s3": {
                "bw": 10,
                "delay": "10ms",
                "loss": 1,
                "max_queue_size": 1000
            }
        },
        "h38": {
            "s1": {
                "bw": 10,
                "delay": "10ms",
                "loss": 1,
                "max_queue_size": 1000
            }
        },
        "h39": {
            "s7": {
                "bw": 10,
                "delay": "10ms",
                "loss": 1,
                "max_queue_size": 1000
            }
        },
        "h40": {
            "s9": {
                "bw": 10,
                "delay": "10ms",
                "loss": 1,
                "max_queue_size": 1000
            }
        },
        "h41": {
            "s13": {
                "bw": 10,
                "delay": "10ms",
                "loss": 1,
                "max_queue_size": 1000
            }
        },
        "h42": {
            "s10": {
                "bw": 10,
                "delay": "10ms",
                "loss": 1,
                "max_queue_size": 1000
            }
        },
        "h43": {
            "s5": {
                "bw": 10,
                "delay": "10ms",
                "loss": 1,
                "max_queue_size": 1000
            }
        },
        "h44": {
            "s13": {
                "bw": 10,
                "delay": "10ms",
                "loss": 1,
                "max_queue_size": 1000
            }
        },
        "h45": {
            "s0": {
                "bw": 10,
                "delay": "10ms",
                "loss": 1,
                "max_queue_size": 1000
            }
        },
        "h46": {
            "s0": {
                "bw": 10,
                "delay": "10ms",
                "loss": 1,
                "max_queue_size": 1000
            }
        },
        "h47": {
            "s15": {
                "bw": 10,
                "delay": "10ms",
                "loss": 1,
                "max_queue_size": 1000
            }
        },
        "h48": {
            "s8": {
                "bw": 10,
                "delay": "10ms",
                "loss": 1,
                "max_queue_size": 1000
            }
        },
        "h49": {
            "s7": {
                "bw": 10,
                "delay": "10ms",
                "loss": 1,
                "max_queue_size": 1000
            }
        },
        "h50": {
            "s4": {
                "bw": 10,
                "delay": "10ms",
                "loss": 1,
                "max_queue_size": 1000
            }
        },
        "h51": {
            "s2": {
                "bw": 10,
                "delay": "10ms",
                "loss": 1,
                "max_queue_size": 1000
            }
        },
        "h52": {
            "s11": {
                "bw": 10,
                "delay": "10ms",
                "loss": 1,
                "max_queue_size": 1000
            }
        },
        "h53": {
            "s6": {
                "bw": 10,
                "delay": "10ms",
                "loss": 1,
                "max_queue_size": 1000
            }
        },
        "h54": {
            "s12": {
                "bw": 10,
                "delay": "10ms",
                "loss": 1,
                "max_queue_size": 1000
            }
        },
        "h55": {
            "s9": {
                "bw": 10,
                "delay": "10ms",
                "loss": 1,
                "max_queue_size": 1000
            }
        },
        "h56": {
            "s9": {
                "bw": 10,
                "delay": "10ms",
                "loss": 1,
                "max_queue_size": 1000
            }
        },
        "h57": {
            "s0": {
                "bw": 10,
                "delay": "10ms",
                "loss": 1,
                "max_queue_size": 1000
            }
        },
        "h58": {
            "s9": {
                "bw": 10,
                "delay": "10ms",
                "loss": 1,
                "max_queue_size": 1000
            }
        },
        "h59": {
            "s7": {
                "bw": 10,
                "delay": "10ms",
                "loss": 1,
                "max_queue_size": 1000
            }
        },
        "h60": {
            "s0": {
                "bw": 10,
                "delay": "10ms",
                "loss": 1,
                "max_queue_size": 1000
            }
        },
        "h61": {
            "s14": {
                "bw": 10,
                "delay": "10ms",
                "loss": 1,
                "max_queue_size": 1000
            }
        },
        "h62": {
            "s12": {
                "bw": 10,
                "delay": "10ms",
                "loss": 1,
                "max_queue_size": 1000
            }
        },
        "h63": {
            "s7": {
                "bw": 10,
                "delay": "10ms",
                "loss": 1,
                "max_queue_size": 1000
            }
        },
        "h64": {
            "s5": {
                "bw": 10,
                "delay": "10ms",
                "loss": 1,
                "max_queue_size": 1000
            }
        },
        "h65": {
            "s7": {
                "bw": 10,
                "delay": "10ms",
                "loss": 1,
                "max_queue_size": 1000
            }
        },
        "h66": {
            "s2": {
                "bw": 10,
                "delay": "10ms",
                "loss": 1,
                "max_queue_size": 1000
            }
        },
        "h67": {
            "s11": {
                "bw": 10,
                "delay": "10ms",
                "loss": 1,
                "max_queue_size": 1000
            }
        },
        "h68": {
            "s11": {
                "bw": 10,
                "delay": "10ms",
                "loss": 1,
                "max_queue_size": 1000
            }
        },
        "h69": {
            "s8": {
                "bw": 10,
                "delay": "10ms",
                "loss": 1,
                "max_queue_size": 1000
            }
        },
        "h70": {
            "s14": {
                "bw": 10,
                "delay": "10ms",
                "loss": 1,
                "max_queue_size": 1000
            }
        },
        "h71": {
            "s8": {
                "bw": 10,
                "delay": "10ms",
                "loss": 1,
                "max_queue_size": 1000
            }
        },
        "h72": {
            "s1": {
                "bw": 10,
                "delay": "10ms",
                "loss": 1,
                "max_queue_size": 1000
            }
        },
        "h73": {
            "s6": {
                "bw": 10,
                "delay": "10ms",
                "loss": 1,
                "max_queue_size": 1000
            }
        },
        "h74": {
            "s6": {
                "bw": 10,
                "delay": "10ms",
                "loss": 1,
                "max_queue_size": 1000
            }
        },
        "h75": {
            "s1": {
                "bw": 10,
                "delay": "10ms",
                "loss": 1,
                "max_queue_size": 1000
            }
        },
        "h76": {
            "s5": {
                "bw": 10,
                "delay": "10ms",
                "loss": 1,
                "max_queue_size": 1000
            }
        },
        "h77": {
            "s1": {
                "bw": 10,
                "delay": "10ms",
                "loss": 1,
                "max_queue_size": 1000
            }
        },
        "h78": {
            "s0": {
                "bw": 10,
                "delay": "10ms",
                "loss": 1,
                "max_queue_size": 1000
            }
        },
        "h79": {
            "s7": {
                "bw": 10,
                "delay": "10ms",
                "loss": 1,
                "max_queue_size": 1000
            }
        },
        "h80": {
            "s11": {
                "bw": 10,
                "delay": "10ms",
                "loss": 1,
                "max_queue_size": 1000
            }
        },
        "h81": {
            "s3": {
                "bw": 10,
                "delay": "10ms",
                "loss": 1,
                "max_queue_size": 1000
            }
        },
        "h82": {
            "s9": {
                "bw": 10,
                "delay": "10ms",
                "loss": 1,
                "max_queue_size": 1000
            }
        },
        "h83": {
            "s12": {
                "bw": 10,
                "delay": "10ms",
                "loss": 1,
                "max_queue_size": 1000
            }
        },
        "h84": {
            "s9": {
                "bw": 10,
                "delay": "10ms",
                "loss": 1,
                "max_queue_size": 1000
            }
        },
        "h85": {
            "s11": {
                "bw": 10,
                "delay": "10ms",
                "loss": 1,
                "max_queue_size": 1000
            }
        },
        "h86": {
            "s6": {
                "bw": 10,
                "delay": "10ms",
                "loss": 1,
                "max_queue_size": 1000
            }
        },
        "h87": {
            "s1": {
                "bw": 10,
                "delay": "10ms",
                "loss": 1,
                "max_queue_size": 1000
            }
        },
        "h88": {
            "s7": {
                "bw": 10,
                "delay": "10ms",
                "loss": 1,
                "max_queue_size": 1000
            }
        },
        "h89": {
            "s3": {
                "bw": 10,
                "delay": "10ms",
                "loss": 1,
                "max_queue_size": 1000
            }
        },
        "h90": {
            "s14": {
                "bw": 10,
                "delay": "10ms",
                "loss": 1,
                "max_queue_size": 1000
            }
        },
        "h91": {
            "s1": {
                "bw": 10,
                "delay": "10ms",
                "loss": 1,
                "max_queue_size": 1000
            }
        },
        "h92": {
            "s0": {
                "bw": 10,
                "delay": "10ms",
                "loss": 1,
                "max_queue_size": 1000
            }
        },
        "h93": {
            "s13": {
                "bw": 10,
                "delay": "10ms",
                "loss": 1,
                "max_queue_size": 1000
            }
        },
        "h94": {
            "s4": {
                "bw": 10,
                "delay": "10ms",
                "loss": 1,
                "max_queue_size": 1000
            }
        },
        "h95": {
            "s9": {
                "bw": 10,
                "delay": "10ms",
                "loss": 1,
                "max_queue_size": 1000
            }
        },
        "h96": {
            "s13": {
                "bw": 10,
                "delay": "10ms",
                "loss": 1,
                "max_queue_size": 1000
            }
        },
        "h97": {
            "s13": {
                "bw": 10,
                "delay": "10ms",
                "loss": 1,
                "max_queue_size": 1000
            }
        },
        "h98": {
            "s15": {
                "bw": 10,
                "delay": "10ms",
                "loss": 1,
                "max_queue_size": 1000
            }
        },
        "h99": {
            "s0": {
                "bw": 10,
                "delay": "10ms",
                "loss": 1,
                "max_queue_size": 1000
            }
        },
        "h100": {
            "s14": {
                "bw": 10,
                "delay": "10ms",
                "loss": 1,
                "max_queue_size": 1000
            }
        }
    }
}